my_weather_mcp/__init__.py
my_weather_mcp/main.py
my_weather_mcp-0.4.3.dist-info/WHEEL
my_weather_mcp-0.4.3.dist-info/entry_points.txt
my_weather_mcp-0.4.3.dist-info/METADATA
my_weather_mcp-0.4.3.dist-info/RECORD
