Metadata-Version: 2.3
Name: my-weather-mcp
Version: 0.4.3
Summary: Add your description here
Author: BasimahLY
Author-email: BasimahLY <934796059@qq.com>
Requires-Dist: httpx>=0.28.1
Requires-Dist: mcp[cli]>=1.25.0
Requires-Python: >=3.10
